{
  "_note": "坪単価/資産性/広さ/取引件数 は主DB(成約)、駅徒歩/築年/耐震/総戸数/共用施設 は従DB(スペック)の実データ。5軸スコアは両DBの実データから算出。スプレッドシートは読み取りのみで未編集。",
  "source": "real",
  "priceMethod": "直近3ヶ月の成約坪単価の移動平均（1取引1票＝単純平均）",
  "priceAnchor": "2026/05",
  "dataYearMax": 2026,
  "generatedAt": "2026-06-27T11:20:29",
  "count": 49,
  "mansions": [
    {
      "name": "センチュリーパークタワー",
      "area": "佃",
      "tsuboPrice": 625,
      "tsuboWindowMonths": 3,
      "txInWindow": 3,
      "tsuboAll": 614,
      "trendPct": 47.4,
      "txCount": 41,
      "medianSqm": 78.0,
      "repLayout": "2LDK",
      "yearMin": 2021,
      "yearMax": 2026,
      "station": "月島",
      "walkMin": 8,
      "builtYear": 1999,
      "ageYears": 27,
      "seismic": "耐震",
      "floors": 54,
      "totalUnits": 756,
      "address": "東京都中央区佃2丁目1-1",
      "modelName": "kachidoki_7",
      "photoUrl": "https://www.wangananalytics.com/images/properties/kachidoki_7.jpg",
      "facilities": {
        "プール": false,
        "ジム": false,
        "バー": false,
        "サウナ": false,
        "コンビニ": false,
        "内廊下": true,
        "オール電化": true
      },
      "specsPending": false,
      "scores": {
        "liv": 61,
        "asset": 76,
        "fac": 48,
        "loc": 83,
        "size": 71
      },
      "realFields": [
        "tsuboPrice",
        "trendPct",
        "txCount",
        "medianSqm",
        "repLayout",
        "station",
        "walkMin",
        "builtYear",
        "seismic",
        "totalUnits",
        "facilities",
        "photoUrl",
        "scores.asset",
        "scores.size",
        "scores.fac",
        "scores.loc",
        "scores.liv"
      ],
      "id": "WM001"
    },
    {
      "name": "パークタワー勝どき",
      "area": "勝どき",
      "tsuboPrice": 1032,
      "tsuboWindowMonths": 3,
      "txInWindow": 6,
      "tsuboAll": 921,
      "trendPct": 28.4,
      "txCount": 166,
      "medianSqm": 71.0,
      "repLayout": "2LDK",
      "yearMin": 2023,
      "yearMax": 2026,
      "station": "勝どき",
      "walkMin": 2,
      "builtYear": 2023,
      "ageYears": 3,
      "seismic": "免震",
      "floors": 45,
      "totalUnits": 2786,
      "address": "東京都中央区勝どき4丁目6",
      "modelName": "kachidoki_6",
      "photoUrl": "https://www.wangananalytics.com/images/properties/kachidoki_6.jpg",
      "facilities": {
        "プール": false,
        "ジム": true,
        "バー": true,
        "サウナ": false,
        "コンビニ": true,
        "内廊下": true,
        "オール電化": false
      },
      "specsPending": false,
      "scores": {
        "liv": 89,
        "asset": 68,
        "fac": 78,
        "loc": 95,
        "size": 64
      },
      "realFields": [
        "tsuboPrice",
        "trendPct",
        "txCount",
        "medianSqm",
        "repLayout",
        "station",
        "walkMin",
        "builtYear",
        "seismic",
        "totalUnits",
        "facilities",
        "photoUrl",
        "scores.asset",
        "scores.size",
        "scores.fac",
        "scores.loc",
        "scores.liv"
      ],
      "id": "WM002"
    },
    {
      "name": "勝どきビュータワー",
      "area": "勝どき",
      "tsuboPrice": 706,
      "tsuboWindowMonths": 3,
      "txInWindow": 2,
      "tsuboAll": 567,
      "trendPct": 92.4,
      "txCount": 47,
      "medianSqm": 57.0,
      "repLayout": "2LDK",
      "yearMin": 2019,
      "yearMax": 2026,
      "station": "勝どき",
      "walkMin": 1,
      "builtYear": 2010,
      "ageYears": 16,
      "seismic": "耐震",
      "floors": 3,
      "totalUnits": 712,
      "address": "東京都中央区勝どき1丁目8-1",
      "modelName": "kachidoki_3",
      "photoUrl": "https://www.wangananalytics.com/images/properties/kachidoki_3.jpg",
      "facilities": {
        "プール": false,
        "ジム": false,
        "バー": false,
        "サウナ": false,
        "コンビニ": true,
        "内廊下": false,
        "オール電化": false
      },
      "specsPending": false,
      "scores": {
        "liv": 63,
        "asset": 97,
        "fac": 48,
        "loc": 96,
        "size": 50
      },
      "realFields": [
        "tsuboPrice",
        "trendPct",
        "txCount",
        "medianSqm",
        "repLayout",
        "station",
        "walkMin",
        "builtYear",
        "seismic",
        "totalUnits",
        "facilities",
        "photoUrl",
        "scores.asset",
        "scores.size",
        "scores.fac",
        "scores.loc",
        "scores.liv"
      ],
      "id": "WM003"
    },
    {
      "name": "KACHIDOKI THE TOWER",
      "area": "勝どき",
      "tsuboPrice": 663,
      "tsuboWindowMonths": 3,
      "txInWindow": 1,
      "tsuboAll": 500,
      "trendPct": 103.5,
      "txCount": 263,
      "medianSqm": 72.0,
      "repLayout": "2LDK",
      "yearMin": 2019,
      "yearMax": 2026,
      "station": "勝どき",
      "walkMin": 6,
      "builtYear": 2016,
      "ageYears": 10,
      "seismic": "制震",
      "floors": 2,
      "totalUnits": 1420,
      "address": "東京都中央区勝どき5丁目3-1",
      "modelName": "kachidoki_5",
      "photoUrl": "https://www.wangananalytics.com/images/properties/kachidoki_5.jpg",
      "facilities": {
        "プール": false,
        "ジム": true,
        "バー": true,
        "サウナ": false,
        "コンビニ": true,
        "内廊下": true,
        "オール電化": true
      },
      "specsPending": false,
      "scores": {
        "liv": 82,
        "asset": 98,
        "fac": 78,
        "loc": 88,
        "size": 65
      },
      "realFields": [
        "tsuboPrice",
        "trendPct",
        "txCount",
        "medianSqm",
        "repLayout",
        "station",
        "walkMin",
        "builtYear",
        "seismic",
        "totalUnits",
        "facilities",
        "photoUrl",
        "scores.asset",
        "scores.size",
        "scores.fac",
        "scores.loc",
        "scores.liv"
      ],
      "id": "WM004"
    },
    {
      "name": "THE TOKYO TOWERS",
      "area": "勝どき",
      "tsuboPrice": 661,
      "tsuboWindowMonths": 3,
      "txInWindow": 7,
      "tsuboAll": 494,
      "trendPct": 66.8,
      "txCount": 142,
      "medianSqm": 84.0,
      "repLayout": "3LDK",
      "yearMin": 2021,
      "yearMax": 2026,
      "station": "勝どき",
      "walkMin": 5,
      "builtYear": 2008,
      "ageYears": 18,
      "seismic": "制震",
      "floors": 58,
      "totalUnits": 1333,
      "address": "東京都中央区勝どき6丁目3",
      "modelName": "kachidoki_4",
      "photoUrl": "https://www.wangananalytics.com/images/properties/kachidoki_4.jpg",
      "facilities": {
        "プール": true,
        "ジム": true,
        "バー": true,
        "サウナ": true,
        "コンビニ": false,
        "内廊下": false,
        "オール電化": true
      },
      "specsPending": false,
      "scores": {
        "liv": 70,
        "asset": 85,
        "fac": 84,
        "loc": 90,
        "size": 77
      },
      "realFields": [
        "tsuboPrice",
        "trendPct",
        "txCount",
        "medianSqm",
        "repLayout",
        "station",
        "walkMin",
        "builtYear",
        "seismic",
        "totalUnits",
        "facilities",
        "photoUrl",
        "scores.asset",
        "scores.size",
        "scores.fac",
        "scores.loc",
        "scores.liv"
      ],
      "id": "WM005"
    },
    {
      "name": "DEUX TOURS CANAL&SPA",
      "area": "晴海",
      "tsuboPrice": 782,
      "tsuboWindowMonths": 3,
      "txInWindow": 9,
      "tsuboAll": 603,
      "trendPct": 86.1,
      "txCount": 316,
      "medianSqm": 71.0,
      "repLayout": "2LDK",
      "yearMin": 2021,
      "yearMax": 2026,
      "station": "勝どき",
      "walkMin": 9,
      "builtYear": 2015,
      "ageYears": 11,
      "seismic": "免震",
      "floors": 1,
      "totalUnits": 1450,
      "address": "東京都中央区晴海3丁目13",
      "modelName": "harumi_11",
      "photoUrl": "https://www.wangananalytics.com/images/properties/harumi_11.jpg",
      "facilities": {
        "プール": false,
        "ジム": true,
        "バー": true,
        "サウナ": false,
        "コンビニ": false,
        "内廊下": true,
        "オール電化": false
      },
      "specsPending": false,
      "scores": {
        "liv": 81,
        "asset": 94,
        "fac": 68,
        "loc": 70,
        "size": 64
      },
      "realFields": [
        "tsuboPrice",
        "trendPct",
        "txCount",
        "medianSqm",
        "repLayout",
        "station",
        "walkMin",
        "builtYear",
        "seismic",
        "totalUnits",
        "facilities",
        "photoUrl",
        "scores.asset",
        "scores.size",
        "scores.fac",
        "scores.loc",
        "scores.liv"
      ],
      "id": "WM006"
    },
    {
      "name": "晴海フラッグ（スカイデュオ）",
      "area": "晴海",
      "tsuboPrice": 758,
      "tsuboWindowMonths": 3,
      "txInWindow": 16,
      "tsuboAll": 789,
      "trendPct": null,
      "txCount": 54,
      "medianSqm": 72.0,
      "repLayout": "3LDK",
      "yearMin": 2024,
      "yearMax": 2026,
      "station": "勝どき",
      "walkMin": 18,
      "builtYear": 2025,
      "ageYears": 1,
      "seismic": "免震",
      "floors": 1,
      "totalUnits": 733,
      "address": "東京都中央区晴海5丁目5-47",
      "modelName": "harumi_9",
      "photoUrl": "https://www.wangananalytics.com/images/properties/harumi_9.jpg",
      "facilities": {
        "プール": false,
        "ジム": true,
        "バー": true,
        "サウナ": false,
        "コンビニ": false,
        "内廊下": true,
        "オール電化": false
      },
      "specsPending": false,
      "scores": {
        "liv": 90,
        "asset": 74,
        "fac": 68,
        "loc": 55,
        "size": 65
      },
      "realFields": [
        "tsuboPrice",
        "trendPct",
        "txCount",
        "medianSqm",
        "repLayout",
        "station",
        "walkMin",
        "builtYear",
        "seismic",
        "totalUnits",
        "facilities",
        "photoUrl",
        "scores.asset",
        "scores.size",
        "scores.fac",
        "scores.loc",
        "scores.liv"
      ],
      "id": "WM007"
    },
    {
      "name": "晴海フラッグ（シーヴィレッジ）",
      "area": "晴海",
      "tsuboPrice": 700,
      "tsuboWindowMonths": 12,
      "txInWindow": 6,
      "tsuboAll": 579,
      "trendPct": null,
      "txCount": 25,
      "medianSqm": 96.0,
      "repLayout": "3LDK",
      "yearMin": 2023,
      "yearMax": 2025,
      "station": "勝どき",
      "walkMin": 16,
      "builtYear": 2023,
      "ageYears": 3,
      "seismic": "耐震",
      "floors": 1,
      "totalUnits": 686,
      "address": "東京都中央区晴海5丁目4-1",
      "modelName": "harumi_10",
      "photoUrl": "https://www.wangananalytics.com/images/properties/harumi_10.jpg",
      "facilities": {
        "プール": false,
        "ジム": true,
        "バー": true,
        "サウナ": false,
        "コンビニ": false,
        "内廊下": false,
        "オール電化": false
      },
      "specsPending": false,
      "scores": {
        "liv": 75,
        "asset": 74,
        "fac": 58,
        "loc": 58,
        "size": 89
      },
      "realFields": [
        "tsuboPrice",
        "trendPct",
        "txCount",
        "medianSqm",
        "repLayout",
        "station",
        "walkMin",
        "builtYear",
        "seismic",
        "totalUnits",
        "facilities",
        "photoUrl",
        "scores.asset",
        "scores.size",
        "scores.fac",
        "scores.loc",
        "scores.liv"
      ],
      "id": "WM008"
    },
    {
      "name": "ザ・パークハウス晴海タワーズ ティアロレジデンス",
      "area": "晴海",
      "tsuboPrice": 680,
      "tsuboWindowMonths": 3,
      "txInWindow": 5,
      "tsuboAll": 472,
      "trendPct": 90.2,
      "txCount": 189,
      "medianSqm": 65.0,
      "repLayout": "2LDK",
      "yearMin": 2019,
      "yearMax": 2026,
      "station": "月島",
      "walkMin": 13,
      "builtYear": 2016,
      "ageYears": 10,
      "seismic": "免震",
      "floors": 49,
      "totalUnits": 862,
      "address": "東京都中央区晴海2丁目3-2",
      "modelName": "harumi_3",
      "photoUrl": "https://www.wangananalytics.com/images/properties/harumi_3.jpg",
      "facilities": {
        "プール": false,
        "ジム": true,
        "バー": true,
        "サウナ": false,
        "コンビニ": true,
        "内廊下": true,
        "オール電化": true
      },
      "specsPending": false,
      "scores": {
        "liv": 86,
        "asset": 96,
        "fac": 78,
        "loc": 63,
        "size": 58
      },
      "realFields": [
        "tsuboPrice",
        "trendPct",
        "txCount",
        "medianSqm",
        "repLayout",
        "station",
        "walkMin",
        "builtYear",
        "seismic",
        "totalUnits",
        "facilities",
        "photoUrl",
        "scores.asset",
        "scores.size",
        "scores.fac",
        "scores.loc",
        "scores.liv"
      ],
      "id": "WM009"
    },
    {
      "name": "晴海フラッグ（パークヴィレッジ）",
      "area": "晴海",
      "tsuboPrice": 677,
      "tsuboWindowMonths": 3,
      "txInWindow": 3,
      "tsuboAll": 576,
      "trendPct": 14.9,
      "txCount": 52,
      "medianSqm": 82.0,
      "repLayout": "3LDK",
      "yearMin": 2023,
      "yearMax": 2026,
      "station": "勝どき",
      "walkMin": 18,
      "builtYear": 2023,
      "ageYears": 3,
      "seismic": "耐震",
      "floors": 1,
      "totalUnits": 915,
      "address": "東京都中央区晴海5丁目6-3",
      "modelName": "harumi_8",
      "photoUrl": "https://www.wangananalytics.com/images/properties/harumi_8.jpg",
      "facilities": {
        "プール": false,
        "ジム": true,
        "バー": true,
        "サウナ": false,
        "コンビニ": true,
        "内廊下": false,
        "オール電化": false
      },
      "specsPending": false,
      "scores": {
        "liv": 76,
        "asset": 62,
        "fac": 68,
        "loc": 55,
        "size": 75
      },
      "realFields": [
        "tsuboPrice",
        "trendPct",
        "txCount",
        "medianSqm",
        "repLayout",
        "station",
        "walkMin",
        "builtYear",
        "seismic",
        "totalUnits",
        "facilities",
        "photoUrl",
        "scores.asset",
        "scores.size",
        "scores.fac",
        "scores.loc",
        "scores.liv"
      ],
      "id": "WM010"
    },
    {
      "name": "パークタワー晴海",
      "area": "晴海",
      "tsuboPrice": 664,
      "tsuboWindowMonths": 3,
      "txInWindow": 8,
      "tsuboAll": 544,
      "trendPct": 70.5,
      "txCount": 181,
      "medianSqm": 71.0,
      "repLayout": "3LDK",
      "yearMin": 2019,
      "yearMax": 2026,
      "station": "月島",
      "walkMin": 12,
      "builtYear": 2019,
      "ageYears": 7,
      "seismic": "免震",
      "floors": 48,
      "totalUnits": 1076,
      "address": "東京都中央区晴海2丁目2-42",
      "modelName": "harumi_1",
      "photoUrl": "https://www.wangananalytics.com/images/properties/harumi_1.jpg",
      "facilities": {
        "プール": false,
        "ジム": true,
        "バー": false,
        "サウナ": false,
        "コンビニ": true,
        "内廊下": true,
        "オール電化": false
      },
      "specsPending": false,
      "scores": {
        "liv": 85,
        "asset": 87,
        "fac": 68,
        "loc": 65,
        "size": 64
      },
      "realFields": [
        "tsuboPrice",
        "trendPct",
        "txCount",
        "medianSqm",
        "repLayout",
        "station",
        "walkMin",
        "builtYear",
        "seismic",
        "totalUnits",
        "facilities",
        "photoUrl",
        "scores.asset",
        "scores.size",
        "scores.fac",
        "scores.loc",
        "scores.liv"
      ],
      "id": "WM011"
    },
    {
      "name": "ベイサイドタワー晴海",
      "area": "晴海",
      "tsuboPrice": 623,
      "tsuboWindowMonths": 3,
      "txInWindow": 3,
      "tsuboAll": 549,
      "trendPct": 64.8,
      "txCount": 67,
      "medianSqm": 57.0,
      "repLayout": "2LDK",
      "yearMin": 2021,
      "yearMax": 2026,
      "station": "勝どき",
      "walkMin": 10,
      "builtYear": 2015,
      "ageYears": 11,
      "seismic": "免震",
      "floors": 33,
      "totalUnits": 352,
      "address": "東京都中央区晴海3丁目16-4",
      "modelName": "harumi_7",
      "photoUrl": "https://www.wangananalytics.com/images/properties/harumi_7.jpg",
      "facilities": {
        "プール": false,
        "ジム": false,
        "バー": false,
        "サウナ": false,
        "コンビニ": false,
        "内廊下": true,
        "オール電化": false
      },
      "specsPending": false,
      "scores": {
        "liv": 80,
        "asset": 84,
        "fac": 48,
        "loc": 68,
        "size": 50
      },
      "realFields": [
        "tsuboPrice",
        "trendPct",
        "txCount",
        "medianSqm",
        "repLayout",
        "station",
        "walkMin",
        "builtYear",
        "seismic",
        "totalUnits",
        "facilities",
        "photoUrl",
        "scores.asset",
        "scores.size",
        "scores.fac",
        "scores.loc",
        "scores.liv"
      ],
      "id": "WM012"
    },
    {
      "name": "ザ・パークハウス晴海タワーズ クロノレジデンス",
      "area": "晴海",
      "tsuboPrice": 558,
      "tsuboWindowMonths": 3,
      "txInWindow": 2,
      "tsuboAll": 439,
      "trendPct": 90.5,
      "txCount": 171,
      "medianSqm": 67.0,
      "repLayout": "2LDK",
      "yearMin": 2019,
      "yearMax": 2026,
      "station": "勝どき",
      "walkMin": 11,
      "builtYear": 2013,
      "ageYears": 13,
      "seismic": "免震",
      "floors": 2,
      "totalUnits": 883,
      "address": "東京都中央区晴海2丁目3-30",
      "modelName": "harumi_2",
      "photoUrl": "https://www.wangananalytics.com/images/properties/harumi_2.jpg",
      "facilities": {
        "プール": false,
        "ジム": true,
        "バー": true,
        "サウナ": false,
        "コンビニ": true,
        "内廊下": true,
        "オール電化": true
      },
      "specsPending": false,
      "scores": {
        "liv": 83,
        "asset": 96,
        "fac": 78,
        "loc": 66,
        "size": 60
      },
      "realFields": [
        "tsuboPrice",
        "trendPct",
        "txCount",
        "medianSqm",
        "repLayout",
        "station",
        "walkMin",
        "builtYear",
        "seismic",
        "totalUnits",
        "facilities",
        "photoUrl",
        "scores.asset",
        "scores.size",
        "scores.fac",
        "scores.loc",
        "scores.liv"
      ],
      "id": "WM013"
    },
    {
      "name": "晴海フラッグ（サンヴィレッジ）",
      "area": "晴海",
      "tsuboPrice": 555,
      "tsuboWindowMonths": 3,
      "txInWindow": 7,
      "tsuboAll": 556,
      "trendPct": 27.8,
      "txCount": 98,
      "medianSqm": 76.0,
      "repLayout": "3LDK",
      "yearMin": 2023,
      "yearMax": 2026,
      "station": "勝どき",
      "walkMin": 17,
      "builtYear": 2023,
      "ageYears": 3,
      "seismic": "耐震",
      "floors": 1,
      "totalUnits": 1089,
      "address": "東京都中央区晴海5丁目5-2",
      "modelName": "harumi_12",
      "photoUrl": "https://www.wangananalytics.com/images/properties/harumi_12.jpg",
      "facilities": {
        "プール": false,
        "ジム": true,
        "バー": true,
        "サウナ": false,
        "コンビニ": false,
        "内廊下": false,
        "オール電化": false
      },
      "specsPending": false,
      "scores": {
        "liv": 75,
        "asset": 68,
        "fac": 58,
        "loc": 57,
        "size": 69
      },
      "realFields": [
        "tsuboPrice",
        "trendPct",
        "txCount",
        "medianSqm",
        "repLayout",
        "station",
        "walkMin",
        "builtYear",
        "seismic",
        "totalUnits",
        "facilities",
        "photoUrl",
        "scores.asset",
        "scores.size",
        "scores.fac",
        "scores.loc",
        "scores.liv"
      ],
      "id": "WM014"
    },
    {
      "name": "晴海テラス",
      "area": "晴海",
      "tsuboPrice": 520,
      "tsuboWindowMonths": 3,
      "txInWindow": 4,
      "tsuboAll": 372,
      "trendPct": 69.0,
      "txCount": 69,
      "medianSqm": 43.0,
      "repLayout": "1LDK",
      "yearMin": 2019,
      "yearMax": 2026,
      "station": "勝どき",
      "walkMin": 10,
      "builtYear": 2009,
      "ageYears": 17,
      "seismic": "耐震",
      "floors": 20,
      "totalUnits": 378,
      "address": "東京都中央区晴海5丁目1-9",
      "modelName": "harumi_5",
      "photoUrl": "https://www.wangananalytics.com/images/properties/harumi_5.jpg",
      "facilities": {
        "プール": false,
        "ジム": false,
        "バー": false,
        "サウナ": false,
        "コンビニ": false,
        "内廊下": false,
        "オール電化": false
      },
      "specsPending": false,
      "scores": {
        "liv": 61,
        "asset": 86,
        "fac": 38,
        "loc": 68,
        "size": 36
      },
      "realFields": [
        "tsuboPrice",
        "trendPct",
        "txCount",
        "medianSqm",
        "repLayout",
        "station",
        "walkMin",
        "builtYear",
        "seismic",
        "totalUnits",
        "facilities",
        "photoUrl",
        "scores.asset",
        "scores.size",
        "scores.fac",
        "scores.loc",
        "scores.liv"
      ],
      "id": "WM015"
    },
    {
      "name": "ザ・晴海レジデンス",
      "area": "晴海",
      "tsuboPrice": 491,
      "tsuboWindowMonths": 3,
      "txInWindow": 1,
      "tsuboAll": 356,
      "trendPct": 75.0,
      "txCount": 82,
      "medianSqm": 76.0,
      "repLayout": "2LDK",
      "yearMin": 2019,
      "yearMax": 2026,
      "station": "勝どき",
      "walkMin": 10,
      "builtYear": 2009,
      "ageYears": 17,
      "seismic": "耐震",
      "floors": 20,
      "totalUnits": 438,
      "address": "東京都中央区晴海5丁目1-17",
      "modelName": "harumi_6",
      "photoUrl": "https://www.wangananalytics.com/images/properties/harumi_6.jpg",
      "facilities": {
        "プール": false,
        "ジム": false,
        "バー": true,
        "サウナ": false,
        "コンビニ": false,
        "内廊下": false,
        "オール電化": false
      },
      "specsPending": false,
      "scores": {
        "liv": 62,
        "asset": 89,
        "fac": 48,
        "loc": 68,
        "size": 69
      },
      "realFields": [
        "tsuboPrice",
        "trendPct",
        "txCount",
        "medianSqm",
        "repLayout",
        "station",
        "walkMin",
        "builtYear",
        "seismic",
        "totalUnits",
        "facilities",
        "photoUrl",
        "scores.asset",
        "scores.size",
        "scores.fac",
        "scores.loc",
        "scores.liv"
      ],
      "id": "WM016"
    },
    {
      "name": "MID TOWER GRAND",
      "area": "月島",
      "tsuboPrice": 922,
      "tsuboWindowMonths": 6,
      "txInWindow": 2,
      "tsuboAll": 657,
      "trendPct": 57.7,
      "txCount": 65,
      "medianSqm": 65.0,
      "repLayout": "3LDK",
      "yearMin": 2021,
      "yearMax": 2026,
      "station": "月島",
      "walkMin": 2,
      "builtYear": 2020,
      "ageYears": 6,
      "seismic": "制震",
      "floors": 32,
      "totalUnits": 503,
      "address": "東京都中央区月島1丁目22-1",
      "modelName": "kachidoki_2",
      "photoUrl": "https://www.wangananalytics.com/images/properties/kachidoki_2.jpg",
      "facilities": {
        "プール": false,
        "ジム": true,
        "バー": true,
        "サウナ": true,
        "コンビニ": false,
        "内廊下": true,
        "オール電化": false
      },
      "specsPending": false,
      "scores": {
        "liv": 82,
        "asset": 81,
        "fac": 78,
        "loc": 93,
        "size": 58
      },
      "realFields": [
        "tsuboPrice",
        "trendPct",
        "txCount",
        "medianSqm",
        "repLayout",
        "station",
        "walkMin",
        "builtYear",
        "seismic",
        "totalUnits",
        "facilities",
        "photoUrl",
        "scores.asset",
        "scores.size",
        "scores.fac",
        "scores.loc",
        "scores.liv"
      ],
      "id": "WM017"
    },
    {
      "name": "キャピタルゲートプレイス ザ・タワー",
      "area": "月島",
      "tsuboPrice": 843,
      "tsuboWindowMonths": 3,
      "txInWindow": 3,
      "tsuboAll": 668,
      "trendPct": 115.9,
      "txCount": 67,
      "medianSqm": 67.0,
      "repLayout": "2LDK",
      "yearMin": 2019,
      "yearMax": 2026,
      "station": "月島",
      "walkMin": 1,
      "builtYear": 2015,
      "ageYears": 11,
      "seismic": "制震",
      "floors": 2,
      "totalUnits": 624,
      "address": "東京都中央区月島1丁目5-1",
      "modelName": "kachidoki_1",
      "photoUrl": "https://www.wangananalytics.com/images/properties/kachidoki_1.jpg",
      "facilities": {
        "プール": false,
        "ジム": true,
        "バー": true,
        "サウナ": false,
        "コンビニ": true,
        "内廊下": true,
        "オール電化": false
      },
      "specsPending": false,
      "scores": {
        "liv": 78,
        "asset": 98,
        "fac": 78,
        "loc": 94,
        "size": 60
      },
      "realFields": [
        "tsuboPrice",
        "trendPct",
        "txCount",
        "medianSqm",
        "repLayout",
        "station",
        "walkMin",
        "builtYear",
        "seismic",
        "totalUnits",
        "facilities",
        "photoUrl",
        "scores.asset",
        "scores.size",
        "scores.fac",
        "scores.loc",
        "scores.liv"
      ],
      "id": "WM018"
    },
    {
      "name": "シティタワーズ東京ベイ",
      "area": "有明",
      "tsuboPrice": 714,
      "tsuboWindowMonths": 3,
      "txInWindow": 8,
      "tsuboAll": 560,
      "trendPct": 63.0,
      "txCount": 219,
      "medianSqm": 55.0,
      "repLayout": "2LDK",
      "yearMin": 2021,
      "yearMax": 2026,
      "station": "有明",
      "walkMin": 3,
      "builtYear": 2019,
      "ageYears": 7,
      "seismic": "免震",
      "floors": 33,
      "totalUnits": 1539,
      "address": "東京都江東区有明2丁目1",
      "modelName": "ariake_5",
      "photoUrl": "https://www.wangananalytics.com/images/properties/ariake_5.jpg",
      "facilities": {
        "プール": false,
        "ジム": false,
        "バー": false,
        "サウナ": false,
        "コンビニ": true,
        "内廊下": true,
        "オール電化": false
      },
      "specsPending": false,
      "scores": {
        "liv": 84,
        "asset": 83,
        "fac": 58,
        "loc": 71,
        "size": 48
      },
      "realFields": [
        "tsuboPrice",
        "trendPct",
        "txCount",
        "medianSqm",
        "repLayout",
        "station",
        "walkMin",
        "builtYear",
        "seismic",
        "totalUnits",
        "facilities",
        "photoUrl",
        "scores.asset",
        "scores.size",
        "scores.fac",
        "scores.loc",
        "scores.liv"
      ],
      "id": "WM019"
    },
    {
      "name": "Brillia 有明 City Tower",
      "area": "有明",
      "tsuboPrice": 648,
      "tsuboWindowMonths": 3,
      "txInWindow": 1,
      "tsuboAll": 381,
      "trendPct": 75.1,
      "txCount": 140,
      "medianSqm": 62.0,
      "repLayout": "2LDK",
      "yearMin": 2019,
      "yearMax": 2026,
      "station": "有明テニスの森",
      "walkMin": 8,
      "builtYear": 2014,
      "ageYears": 12,
      "seismic": "免震",
      "floors": 33,
      "totalUnits": 600,
      "address": "東京都江東区有明1丁目5-2",
      "modelName": "ariake_3",
      "photoUrl": "https://www.wangananalytics.com/images/properties/ariake_3.jpg",
      "facilities": {
        "プール": false,
        "ジム": true,
        "バー": true,
        "サウナ": false,
        "コンビニ": false,
        "内廊下": true,
        "オール電化": false
      },
      "specsPending": false,
      "scores": {
        "liv": 80,
        "asset": 89,
        "fac": 68,
        "loc": 63,
        "size": 55
      },
      "realFields": [
        "tsuboPrice",
        "trendPct",
        "txCount",
        "medianSqm",
        "repLayout",
        "station",
        "walkMin",
        "builtYear",
        "seismic",
        "totalUnits",
        "facilities",
        "photoUrl",
        "scores.asset",
        "scores.size",
        "scores.fac",
        "scores.loc",
        "scores.liv"
      ],
      "id": "WM020"
    },
    {
      "name": "BrilliaTower有明 MID CROSS",
      "area": "有明",
      "tsuboPrice": 624,
      "tsuboWindowMonths": 3,
      "txInWindow": 3,
      "tsuboAll": 508,
      "trendPct": 43.5,
      "txCount": 33,
      "medianSqm": 55.0,
      "repLayout": "1LDK",
      "yearMin": 2022,
      "yearMax": 2026,
      "station": "お台場海浜公園",
      "walkMin": 9,
      "builtYear": 2021,
      "ageYears": 5,
      "seismic": "免震",
      "floors": 32,
      "totalUnits": 300,
      "address": "東京都江東区有明1丁目6-30",
      "modelName": "ariake_4",
      "photoUrl": "https://www.wangananalytics.com/images/properties/ariake_4.jpg",
      "facilities": {
        "プール": false,
        "ジム": false,
        "バー": true,
        "サウナ": false,
        "コンビニ": false,
        "内廊下": true,
        "オール電化": false
      },
      "specsPending": false,
      "scores": {
        "liv": 86,
        "asset": 75,
        "fac": 58,
        "loc": 62,
        "size": 48
      },
      "realFields": [
        "tsuboPrice",
        "trendPct",
        "txCount",
        "medianSqm",
        "repLayout",
        "station",
        "walkMin",
        "builtYear",
        "seismic",
        "totalUnits",
        "facilities",
        "photoUrl",
        "scores.asset",
        "scores.size",
        "scores.fac",
        "scores.loc",
        "scores.liv"
      ],
      "id": "WM021"
    },
    {
      "name": "Brillia 有明 Sky Tower",
      "area": "有明",
      "tsuboPrice": 599,
      "tsuboWindowMonths": 3,
      "txInWindow": 7,
      "tsuboAll": 386,
      "trendPct": 89.1,
      "txCount": 227,
      "medianSqm": 68.0,
      "repLayout": "3LDK",
      "yearMin": 2019,
      "yearMax": 2026,
      "station": "有明テニスの森",
      "walkMin": 7,
      "builtYear": 2010,
      "ageYears": 16,
      "seismic": "制震",
      "floors": 33,
      "totalUnits": 1089,
      "address": "東京都江東区有明1丁目4-20",
      "modelName": "ariake_2",
      "photoUrl": "https://www.wangananalytics.com/images/properties/ariake_2.jpg",
      "facilities": {
        "プール": true,
        "ジム": true,
        "バー": true,
        "サウナ": false,
        "コンビニ": false,
        "内廊下": false,
        "オール電化": true
      },
      "specsPending": false,
      "scores": {
        "liv": 71,
        "asset": 95,
        "fac": 74,
        "loc": 65,
        "size": 61
      },
      "realFields": [
        "tsuboPrice",
        "trendPct",
        "txCount",
        "medianSqm",
        "repLayout",
        "station",
        "walkMin",
        "builtYear",
        "seismic",
        "totalUnits",
        "facilities",
        "photoUrl",
        "scores.asset",
        "scores.size",
        "scores.fac",
        "scores.loc",
        "scores.liv"
      ],
      "id": "WM022"
    },
    {
      "name": "Brillia Mare 有明 TOWER&GARDEN",
      "area": "有明",
      "tsuboPrice": 580,
      "tsuboWindowMonths": 3,
      "txInWindow": 3,
      "tsuboAll": 367,
      "trendPct": 95.8,
      "txCount": 195,
      "medianSqm": 66.0,
      "repLayout": "2LDK",
      "yearMin": 2019,
      "yearMax": 2026,
      "station": "有明テニスの森",
      "walkMin": 5,
      "builtYear": 2008,
      "ageYears": 18,
      "seismic": "耐震",
      "floors": 33,
      "totalUnits": 1085,
      "address": "東京都江東区有明1丁目4-11",
      "modelName": "ariake_1",
      "photoUrl": "https://www.wangananalytics.com/images/properties/ariake_1.jpg",
      "facilities": {
        "プール": true,
        "ジム": true,
        "バー": true,
        "サウナ": true,
        "コンビニ": true,
        "内廊下": false,
        "オール電化": false
      },
      "specsPending": false,
      "scores": {
        "liv": 64,
        "asset": 98,
        "fac": 94,
        "loc": 68,
        "size": 59
      },
      "realFields": [
        "tsuboPrice",
        "trendPct",
        "txCount",
        "medianSqm",
        "repLayout",
        "station",
        "walkMin",
        "builtYear",
        "seismic",
        "totalUnits",
        "facilities",
        "photoUrl",
        "scores.asset",
        "scores.size",
        "scores.fac",
        "scores.loc",
        "scores.liv"
      ],
      "id": "WM023"
    },
    {
      "name": "シティタワー有明",
      "area": "有明",
      "tsuboPrice": 569,
      "tsuboWindowMonths": 3,
      "txInWindow": 4,
      "tsuboAll": 371,
      "trendPct": 91.2,
      "txCount": 120,
      "medianSqm": 61.0,
      "repLayout": "2LDK",
      "yearMin": 2019,
      "yearMax": 2026,
      "station": "有明テニスの森",
      "walkMin": 10,
      "builtYear": 2009,
      "ageYears": 17,
      "seismic": "免震",
      "floors": 33,
      "totalUnits": 483,
      "address": "東京都江東区有明1丁目1-17",
      "modelName": "ariake_6",
      "photoUrl": "https://www.wangananalytics.com/images/properties/ariake_6.jpg",
      "facilities": {
        "プール": false,
        "ジム": true,
        "バー": false,
        "サウナ": false,
        "コンビニ": true,
        "内廊下": true,
        "オール電化": false
      },
      "specsPending": false,
      "scores": {
        "liv": 76,
        "asset": 96,
        "fac": 68,
        "loc": 60,
        "size": 54
      },
      "realFields": [
        "tsuboPrice",
        "trendPct",
        "txCount",
        "medianSqm",
        "repLayout",
        "station",
        "walkMin",
        "builtYear",
        "seismic",
        "totalUnits",
        "facilities",
        "photoUrl",
        "scores.asset",
        "scores.size",
        "scores.fac",
        "scores.loc",
        "scores.liv"
      ],
      "id": "WM024"
    },
    {
      "name": "プレミスト有明ガーデンズ",
      "area": "有明",
      "tsuboPrice": 561,
      "tsuboWindowMonths": 12,
      "txInWindow": 6,
      "tsuboAll": 434,
      "trendPct": 45.7,
      "txCount": 28,
      "medianSqm": 65.0,
      "repLayout": "3LDK",
      "yearMin": 2021,
      "yearMax": 2025,
      "station": "有明テニスの森",
      "walkMin": 2,
      "builtYear": 2020,
      "ageYears": 6,
      "seismic": "免震",
      "floors": 15,
      "totalUnits": 258,
      "address": "東京都江東区有明1丁目3-14",
      "modelName": "ariake_9",
      "photoUrl": "https://www.wangananalytics.com/images/properties/ariake_9.jpg",
      "facilities": {
        "プール": false,
        "ジム": false,
        "バー": true,
        "サウナ": false,
        "コンビニ": false,
        "内廊下": false,
        "オール電化": false
      },
      "specsPending": false,
      "scores": {
        "liv": 80,
        "asset": 76,
        "fac": 48,
        "loc": 73,
        "size": 58
      },
      "realFields": [
        "tsuboPrice",
        "trendPct",
        "txCount",
        "medianSqm",
        "repLayout",
        "station",
        "walkMin",
        "builtYear",
        "seismic",
        "totalUnits",
        "facilities",
        "photoUrl",
        "scores.asset",
        "scores.size",
        "scores.fac",
        "scores.loc",
        "scores.liv"
      ],
      "id": "WM025"
    },
    {
      "name": "ガレリアグランデ",
      "area": "有明",
      "tsuboPrice": 508,
      "tsuboWindowMonths": 3,
      "txInWindow": 4,
      "tsuboAll": 320,
      "trendPct": 112.6,
      "txCount": 74,
      "medianSqm": 73.5,
      "repLayout": "1SLDK",
      "yearMin": 2019,
      "yearMax": 2026,
      "station": "有明テニスの森",
      "walkMin": 7,
      "builtYear": 2006,
      "ageYears": 20,
      "seismic": "耐震",
      "floors": 27,
      "totalUnits": 413,
      "address": "東京都江東区有明1丁目2-11",
      "modelName": "ariake_8",
      "photoUrl": "https://www.wangananalytics.com/images/properties/ariake_8.jpg",
      "facilities": {
        "プール": true,
        "ジム": true,
        "バー": true,
        "サウナ": false,
        "コンビニ": false,
        "内廊下": true,
        "オール電化": false
      },
      "specsPending": false,
      "scores": {
        "liv": 66,
        "asset": 98,
        "fac": 84,
        "loc": 65,
        "size": 66
      },
      "realFields": [
        "tsuboPrice",
        "trendPct",
        "txCount",
        "medianSqm",
        "repLayout",
        "station",
        "walkMin",
        "builtYear",
        "seismic",
        "totalUnits",
        "facilities",
        "photoUrl",
        "scores.asset",
        "scores.size",
        "scores.fac",
        "scores.loc",
        "scores.liv"
      ],
      "id": "WM026"
    },
    {
      "name": "オリゾンマーレ",
      "area": "有明",
      "tsuboPrice": 491,
      "tsuboWindowMonths": 3,
      "txInWindow": 3,
      "tsuboAll": 336,
      "trendPct": 96.2,
      "txCount": 74,
      "medianSqm": 63.5,
      "repLayout": "1LDK",
      "yearMin": 2019,
      "yearMax": 2026,
      "station": "有明テニスの森",
      "walkMin": 3,
      "builtYear": 2004,
      "ageYears": 22,
      "seismic": "耐震",
      "floors": null,
      "totalUnits": 398,
      "address": "東京都江東区有明1丁目3-14",
      "modelName": "ariake_7",
      "photoUrl": "https://www.wangananalytics.com/images/properties/ariake_7.jpg",
      "facilities": {
        "プール": true,
        "ジム": true,
        "バー": true,
        "サウナ": false,
        "コンビニ": false,
        "内廊下": true,
        "オール電化": false
      },
      "specsPending": false,
      "scores": {
        "liv": 64,
        "asset": 98,
        "fac": 84,
        "loc": 71,
        "size": 56
      },
      "realFields": [
        "tsuboPrice",
        "trendPct",
        "txCount",
        "medianSqm",
        "repLayout",
        "station",
        "walkMin",
        "builtYear",
        "seismic",
        "totalUnits",
        "facilities",
        "photoUrl",
        "scores.asset",
        "scores.size",
        "scores.fac",
        "scores.loc",
        "scores.liv"
      ],
      "id": "WM027"
    },
    {
      "name": "プラウドシティ東雲キャナルマークス",
      "area": "東雲",
      "tsuboPrice": 578,
      "tsuboWindowMonths": 6,
      "txInWindow": 2,
      "tsuboAll": 436,
      "trendPct": 42.3,
      "txCount": 79,
      "medianSqm": 70.0,
      "repLayout": "3LDK",
      "yearMin": 2022,
      "yearMax": 2026,
      "station": "豊洲",
      "walkMin": 10,
      "builtYear": 2020,
      "ageYears": 6,
      "seismic": "耐震",
      "floors": 15,
      "totalUnits": 472,
      "address": "東京都江東区東雲1丁目10-14",
      "modelName": "shinonome_2",
      "photoUrl": "https://www.wangananalytics.com/images/properties/shinonome_2.jpg",
      "facilities": {
        "プール": false,
        "ジム": false,
        "バー": true,
        "サウナ": false,
        "コンビニ": false,
        "内廊下": false,
        "オール電化": false
      },
      "specsPending": false,
      "scores": {
        "liv": 72,
        "asset": 74,
        "fac": 48,
        "loc": 62,
        "size": 63
      },
      "realFields": [
        "tsuboPrice",
        "trendPct",
        "txCount",
        "medianSqm",
        "repLayout",
        "station",
        "walkMin",
        "builtYear",
        "seismic",
        "totalUnits",
        "facilities",
        "photoUrl",
        "scores.asset",
        "scores.size",
        "scores.fac",
        "scores.loc",
        "scores.liv"
      ],
      "id": "WM028"
    },
    {
      "name": "パークタワー東雲",
      "area": "東雲",
      "tsuboPrice": 576,
      "tsuboWindowMonths": 3,
      "txInWindow": 3,
      "tsuboAll": 401,
      "trendPct": 96.0,
      "txCount": 132,
      "medianSqm": 70.0,
      "repLayout": "2LDK",
      "yearMin": 2019,
      "yearMax": 2026,
      "station": "東雲",
      "walkMin": 7,
      "builtYear": 2014,
      "ageYears": 12,
      "seismic": "免震",
      "floors": 43,
      "totalUnits": 585,
      "address": "東京都江東区東雲1丁目9-4",
      "modelName": "shinonome_7",
      "photoUrl": "https://www.wangananalytics.com/images/properties/shinonome_7.jpg",
      "facilities": {
        "プール": false,
        "ジム": false,
        "バー": false,
        "サウナ": false,
        "コンビニ": false,
        "内廊下": false,
        "オール電化": true
      },
      "specsPending": false,
      "scores": {
        "liv": 77,
        "asset": 98,
        "fac": 38,
        "loc": 67,
        "size": 63
      },
      "realFields": [
        "tsuboPrice",
        "trendPct",
        "txCount",
        "medianSqm",
        "repLayout",
        "station",
        "walkMin",
        "builtYear",
        "seismic",
        "totalUnits",
        "facilities",
        "photoUrl",
        "scores.asset",
        "scores.size",
        "scores.fac",
        "scores.loc",
        "scores.liv"
      ],
      "id": "WM029"
    },
    {
      "name": "プラウドタワー東雲キャナルコート",
      "area": "東雲",
      "tsuboPrice": 548,
      "tsuboWindowMonths": 3,
      "txInWindow": 2,
      "tsuboAll": 352,
      "trendPct": 106.1,
      "txCount": 108,
      "medianSqm": 76.0,
      "repLayout": "3LDK",
      "yearMin": 2019,
      "yearMax": 2026,
      "station": "豊洲",
      "walkMin": 11,
      "builtYear": 2012,
      "ageYears": 14,
      "seismic": "耐震",
      "floors": 52,
      "totalUnits": 600,
      "address": "東京都江東区東雲1丁目9-50",
      "modelName": "shinonome_1",
      "photoUrl": "https://www.wangananalytics.com/images/properties/shinonome_1.jpg",
      "facilities": {
        "プール": false,
        "ジム": true,
        "バー": true,
        "サウナ": false,
        "コンビニ": false,
        "内廊下": false,
        "オール電化": true
      },
      "specsPending": false,
      "scores": {
        "liv": 68,
        "asset": 98,
        "fac": 58,
        "loc": 60,
        "size": 69
      },
      "realFields": [
        "tsuboPrice",
        "trendPct",
        "txCount",
        "medianSqm",
        "repLayout",
        "station",
        "walkMin",
        "builtYear",
        "seismic",
        "totalUnits",
        "facilities",
        "photoUrl",
        "scores.asset",
        "scores.size",
        "scores.fac",
        "scores.loc",
        "scores.liv"
      ],
      "id": "WM030"
    },
    {
      "name": "ザ 湾岸タワー レックスガーデン",
      "area": "東雲",
      "tsuboPrice": 512,
      "tsuboWindowMonths": 3,
      "txInWindow": 3,
      "tsuboAll": 326,
      "trendPct": 77.1,
      "txCount": 98,
      "medianSqm": 62.0,
      "repLayout": "2LDK",
      "yearMin": 2019,
      "yearMax": 2026,
      "station": "東雲",
      "walkMin": 3,
      "builtYear": 2012,
      "ageYears": 14,
      "seismic": "免震",
      "floors": 31,
      "totalUnits": 456,
      "address": "東京都江東区東雲2丁目2-14",
      "modelName": "shinonome_8",
      "photoUrl": "https://www.wangananalytics.com/images/properties/shinonome_8.jpg",
      "facilities": {
        "プール": false,
        "ジム": false,
        "バー": false,
        "サウナ": false,
        "コンビニ": false,
        "内廊下": true,
        "オール電化": false
      },
      "specsPending": false,
      "scores": {
        "liv": 77,
        "asset": 90,
        "fac": 48,
        "loc": 73,
        "size": 55
      },
      "realFields": [
        "tsuboPrice",
        "trendPct",
        "txCount",
        "medianSqm",
        "repLayout",
        "station",
        "walkMin",
        "builtYear",
        "seismic",
        "totalUnits",
        "facilities",
        "photoUrl",
        "scores.asset",
        "scores.size",
        "scores.fac",
        "scores.loc",
        "scores.liv"
      ],
      "id": "WM031"
    },
    {
      "name": "キャナルファーストタワー",
      "area": "東雲",
      "tsuboPrice": 482,
      "tsuboWindowMonths": 3,
      "txInWindow": 2,
      "tsuboAll": 311,
      "trendPct": 90.3,
      "txCount": 64,
      "medianSqm": 76.0,
      "repLayout": "2LDK",
      "yearMin": 2019,
      "yearMax": 2026,
      "station": "辰巳",
      "walkMin": 8,
      "builtYear": 2008,
      "ageYears": 18,
      "seismic": "耐震",
      "floors": 42,
      "totalUnits": 415,
      "address": "東京都江東区東雲1丁目9-42",
      "modelName": "shinonome_4",
      "photoUrl": "https://www.wangananalytics.com/images/properties/shinonome_4.jpg",
      "facilities": {
        "プール": false,
        "ジム": true,
        "バー": true,
        "サウナ": false,
        "コンビニ": false,
        "内廊下": false,
        "オール電化": true
      },
      "specsPending": false,
      "scores": {
        "liv": 64,
        "asset": 96,
        "fac": 58,
        "loc": 65,
        "size": 69
      },
      "realFields": [
        "tsuboPrice",
        "trendPct",
        "txCount",
        "medianSqm",
        "repLayout",
        "station",
        "walkMin",
        "builtYear",
        "seismic",
        "totalUnits",
        "facilities",
        "photoUrl",
        "scores.asset",
        "scores.size",
        "scores.fac",
        "scores.loc",
        "scores.liv"
      ],
      "id": "WM032"
    },
    {
      "name": "BEACON Tower Residence",
      "area": "東雲",
      "tsuboPrice": 444,
      "tsuboWindowMonths": 3,
      "txInWindow": 2,
      "tsuboAll": 309,
      "trendPct": 86.8,
      "txCount": 93,
      "medianSqm": 83.0,
      "repLayout": "2LDK",
      "yearMin": 2019,
      "yearMax": 2026,
      "station": "辰巳",
      "walkMin": 9,
      "builtYear": 2009,
      "ageYears": 17,
      "seismic": "免震",
      "floors": 41,
      "totalUnits": 440,
      "address": "東京都江東区東雲1丁目9-43",
      "modelName": "shinonome_3",
      "photoUrl": "https://www.wangananalytics.com/images/properties/shinonome_3.jpg",
      "facilities": {
        "プール": false,
        "ジム": false,
        "バー": true,
        "サウナ": false,
        "コンビニ": false,
        "内廊下": false,
        "オール電化": true
      },
      "specsPending": false,
      "scores": {
        "liv": 73,
        "asset": 94,
        "fac": 48,
        "loc": 64,
        "size": 76
      },
      "realFields": [
        "tsuboPrice",
        "trendPct",
        "txCount",
        "medianSqm",
        "repLayout",
        "station",
        "walkMin",
        "builtYear",
        "seismic",
        "totalUnits",
        "facilities",
        "photoUrl",
        "scores.asset",
        "scores.size",
        "scores.fac",
        "scores.loc",
        "scores.liv"
      ],
      "id": "WM033"
    },
    {
      "name": "アップルタワー東京キャナルコート",
      "area": "東雲",
      "tsuboPrice": 442,
      "tsuboWindowMonths": 6,
      "txInWindow": 4,
      "tsuboAll": 295,
      "trendPct": 90.7,
      "txCount": 71,
      "medianSqm": 75.0,
      "repLayout": "3LDK",
      "yearMin": 2019,
      "yearMax": 2026,
      "station": "辰巳",
      "walkMin": 7,
      "builtYear": 2007,
      "ageYears": 19,
      "seismic": "耐震",
      "floors": 44,
      "totalUnits": 440,
      "address": "東京都江東区東雲1丁目9-41",
      "modelName": "shinonome_5",
      "photoUrl": "https://www.wangananalytics.com/images/properties/shinonome_5.jpg",
      "facilities": {
        "プール": false,
        "ジム": false,
        "バー": false,
        "サウナ": false,
        "コンビニ": false,
        "内廊下": false,
        "オール電化": false
      },
      "specsPending": false,
      "scores": {
        "liv": 59,
        "asset": 96,
        "fac": 38,
        "loc": 67,
        "size": 68
      },
      "realFields": [
        "tsuboPrice",
        "trendPct",
        "txCount",
        "medianSqm",
        "repLayout",
        "station",
        "walkMin",
        "builtYear",
        "seismic",
        "totalUnits",
        "facilities",
        "photoUrl",
        "scores.asset",
        "scores.size",
        "scores.fac",
        "scores.loc",
        "scores.liv"
      ],
      "id": "WM034"
    },
    {
      "name": "Wコンフォートタワーズ",
      "area": "東雲",
      "tsuboPrice": 426,
      "tsuboWindowMonths": 3,
      "txInWindow": 6,
      "tsuboAll": 315,
      "trendPct": 94.4,
      "txCount": 123,
      "medianSqm": 89.0,
      "repLayout": "2LDK",
      "yearMin": 2019,
      "yearMax": 2026,
      "station": "辰巳",
      "walkMin": 6,
      "builtYear": null,
      "ageYears": null,
      "seismic": "制震",
      "floors": 45,
      "totalUnits": 1149,
      "address": "東京都江東区東雲1丁目9番32号",
      "modelName": "shinonome_6",
      "photoUrl": "https://www.wangananalytics.com/images/properties/shinonome_6.jpg",
      "facilities": {
        "プール": false,
        "ジム": true,
        "バー": false,
        "サウナ": false,
        "コンビニ": false,
        "内廊下": false,
        "オール電化": false
      },
      "specsPending": false,
      "scores": {
        "liv": 67,
        "asset": 97,
        "fac": 48,
        "loc": 68,
        "size": 82
      },
      "realFields": [
        "tsuboPrice",
        "trendPct",
        "txCount",
        "medianSqm",
        "repLayout",
        "station",
        "walkMin",
        "builtYear",
        "seismic",
        "totalUnits",
        "facilities",
        "photoUrl",
        "scores.asset",
        "scores.size",
        "scores.fac",
        "scores.loc",
        "scores.liv"
      ],
      "id": "WM035"
    },
    {
      "name": "ブランズタワー豊洲",
      "area": "豊洲",
      "tsuboPrice": 873,
      "tsuboWindowMonths": 3,
      "txInWindow": 3,
      "tsuboAll": 705,
      "trendPct": 49.7,
      "txCount": 123,
      "medianSqm": 61.0,
      "repLayout": "2LDK",
      "yearMin": 2022,
      "yearMax": 2026,
      "station": "豊洲",
      "walkMin": 4,
      "builtYear": 2021,
      "ageYears": 5,
      "seismic": "免震",
      "floors": 48,
      "totalUnits": 1152,
      "address": "東京都江東区豊洲5丁目1-13",
      "modelName": "toyosu_9",
      "photoUrl": "https://www.wangananalytics.com/images/properties/toyosu_9.jpg",
      "facilities": {
        "プール": false,
        "ジム": true,
        "バー": true,
        "サウナ": false,
        "コンビニ": false,
        "内廊下": true,
        "オール電化": false
      },
      "specsPending": false,
      "scores": {
        "liv": 87,
        "asset": 77,
        "fac": 68,
        "loc": 92,
        "size": 54
      },
      "realFields": [
        "tsuboPrice",
        "trendPct",
        "txCount",
        "medianSqm",
        "repLayout",
        "station",
        "walkMin",
        "builtYear",
        "seismic",
        "totalUnits",
        "facilities",
        "photoUrl",
        "scores.asset",
        "scores.size",
        "scores.fac",
        "scores.loc",
        "scores.liv"
      ],
      "id": "WM036"
    },
    {
      "name": "アーバンドック パークシティ豊洲 タワーA",
      "area": "豊洲",
      "tsuboPrice": 761,
      "tsuboWindowMonths": 3,
      "txInWindow": 1,
      "tsuboAll": 441,
      "trendPct": 109.1,
      "txCount": 138,
      "medianSqm": 71.0,
      "repLayout": "2LDK",
      "yearMin": 2017,
      "yearMax": 2026,
      "station": "豊洲",
      "walkMin": 8,
      "builtYear": 2008,
      "ageYears": 18,
      "seismic": "制震",
      "floors": 53,
      "totalUnits": 1020,
      "address": "東京都江東区豊洲2丁目5-1",
      "modelName": "toyosu_3",
      "photoUrl": "https://www.wangananalytics.com/images/properties/toyosu_3.jpg",
      "facilities": {
        "プール": true,
        "ジム": false,
        "バー": true,
        "サウナ": true,
        "コンビニ": true,
        "内廊下": false,
        "オール電化": false
      },
      "specsPending": false,
      "scores": {
        "liv": 67,
        "asset": 98,
        "fac": 84,
        "loc": 85,
        "size": 64
      },
      "realFields": [
        "tsuboPrice",
        "trendPct",
        "txCount",
        "medianSqm",
        "repLayout",
        "station",
        "walkMin",
        "builtYear",
        "seismic",
        "totalUnits",
        "facilities",
        "photoUrl",
        "scores.asset",
        "scores.size",
        "scores.fac",
        "scores.loc",
        "scores.liv"
      ],
      "id": "WM037"
    },
    {
      "name": "パークホームズ豊洲ザ レジデンス",
      "area": "豊洲",
      "tsuboPrice": 756,
      "tsuboWindowMonths": 3,
      "txInWindow": 2,
      "tsuboAll": 450,
      "trendPct": 113.7,
      "txCount": 112,
      "medianSqm": 72.5,
      "repLayout": "3LDK",
      "yearMin": 2017,
      "yearMax": 2026,
      "station": "豊洲",
      "walkMin": 5,
      "builtYear": 2016,
      "ageYears": 10,
      "seismic": "免震",
      "floors": 22,
      "totalUnits": 693,
      "address": "東京都江東区豊洲5丁目6-29",
      "modelName": "toyosu_10",
      "photoUrl": "https://www.wangananalytics.com/images/properties/toyosu_10.jpg",
      "facilities": {
        "プール": false,
        "ジム": false,
        "バー": false,
        "サウナ": false,
        "コンビニ": false,
        "内廊下": false,
        "オール電化": false
      },
      "specsPending": false,
      "scores": {
        "liv": 75,
        "asset": 98,
        "fac": 38,
        "loc": 90,
        "size": 66
      },
      "realFields": [
        "tsuboPrice",
        "trendPct",
        "txCount",
        "medianSqm",
        "repLayout",
        "station",
        "walkMin",
        "builtYear",
        "seismic",
        "totalUnits",
        "facilities",
        "photoUrl",
        "scores.asset",
        "scores.size",
        "scores.fac",
        "scores.loc",
        "scores.liv"
      ],
      "id": "WM038"
    },
    {
      "name": "BAYZ TOWER&GARDEN",
      "area": "豊洲",
      "tsuboPrice": 698,
      "tsuboWindowMonths": 3,
      "txInWindow": 2,
      "tsuboAll": 440,
      "trendPct": 117.7,
      "txCount": 127,
      "medianSqm": 74.0,
      "repLayout": "2LDK",
      "yearMin": 2017,
      "yearMax": 2026,
      "station": "新豊洲",
      "walkMin": 6,
      "builtYear": 2016,
      "ageYears": 10,
      "seismic": "免震",
      "floors": 32,
      "totalUnits": 550,
      "address": "東京都江東区豊洲6丁目2-29",
      "modelName": "toyosu_2",
      "photoUrl": "https://www.wangananalytics.com/images/properties/toyosu_2.jpg",
      "facilities": {
        "プール": true,
        "ジム": true,
        "バー": true,
        "サウナ": false,
        "コンビニ": true,
        "内廊下": false,
        "オール電化": true
      },
      "specsPending": false,
      "scores": {
        "liv": 81,
        "asset": 98,
        "fac": 84,
        "loc": 88,
        "size": 67
      },
      "realFields": [
        "tsuboPrice",
        "trendPct",
        "txCount",
        "medianSqm",
        "repLayout",
        "station",
        "walkMin",
        "builtYear",
        "seismic",
        "totalUnits",
        "facilities",
        "photoUrl",
        "scores.asset",
        "scores.size",
        "scores.fac",
        "scores.loc",
        "scores.liv"
      ],
      "id": "WM039"
    },
    {
      "name": "SKYZ TOWER&GARDEN",
      "area": "豊洲",
      "tsuboPrice": 696,
      "tsuboWindowMonths": 3,
      "txInWindow": 6,
      "tsuboAll": 443,
      "trendPct": 128.7,
      "txCount": 236,
      "medianSqm": 73.0,
      "repLayout": "3LDK",
      "yearMin": 2017,
      "yearMax": 2026,
      "station": "新豊洲",
      "walkMin": 5,
      "builtYear": 2014,
      "ageYears": 12,
      "seismic": "免震",
      "floors": 44,
      "totalUnits": 1110,
      "address": "東京都江東区豊洲6丁目2-31",
      "modelName": "toyosu_1",
      "photoUrl": "https://www.wangananalytics.com/images/properties/toyosu_1.jpg",
      "facilities": {
        "プール": true,
        "ジム": true,
        "バー": true,
        "サウナ": false,
        "コンビニ": true,
        "内廊下": true,
        "オール電化": true
      },
      "specsPending": false,
      "scores": {
        "liv": 85,
        "asset": 98,
        "fac": 94,
        "loc": 90,
        "size": 66
      },
      "realFields": [
        "tsuboPrice",
        "trendPct",
        "txCount",
        "medianSqm",
        "repLayout",
        "station",
        "walkMin",
        "builtYear",
        "seismic",
        "totalUnits",
        "facilities",
        "photoUrl",
        "scores.asset",
        "scores.size",
        "scores.fac",
        "scores.loc",
        "scores.liv"
      ],
      "id": "WM040"
    },
    {
      "name": "THE TOYOSU TOWER",
      "area": "豊洲",
      "tsuboPrice": 675,
      "tsuboWindowMonths": 3,
      "txInWindow": 5,
      "tsuboAll": 425,
      "trendPct": 109.4,
      "txCount": 189,
      "medianSqm": 71.0,
      "repLayout": "2LDK",
      "yearMin": 2017,
      "yearMax": 2026,
      "station": "豊洲",
      "walkMin": 6,
      "builtYear": 2008,
      "ageYears": 18,
      "seismic": "免震",
      "floors": 43,
      "totalUnits": 825,
      "address": "東京都江東区豊洲3丁目6-5",
      "modelName": "toyosu_7",
      "photoUrl": "https://www.wangananalytics.com/images/properties/toyosu_7.jpg",
      "facilities": {
        "プール": false,
        "ジム": true,
        "バー": false,
        "サウナ": false,
        "コンビニ": true,
        "内廊下": false,
        "オール電化": true
      },
      "specsPending": false,
      "scores": {
        "liv": 72,
        "asset": 98,
        "fac": 58,
        "loc": 88,
        "size": 64
      },
      "realFields": [
        "tsuboPrice",
        "trendPct",
        "txCount",
        "medianSqm",
        "repLayout",
        "station",
        "walkMin",
        "builtYear",
        "seismic",
        "totalUnits",
        "facilities",
        "photoUrl",
        "scores.asset",
        "scores.size",
        "scores.fac",
        "scores.loc",
        "scores.liv"
      ],
      "id": "WM041"
    },
    {
      "name": "シティタワーズ豊洲 ザ・ツイン",
      "area": "豊洲",
      "tsuboPrice": 642,
      "tsuboWindowMonths": 3,
      "txInWindow": 8,
      "tsuboAll": 402,
      "trendPct": 115.6,
      "txCount": 324,
      "medianSqm": 77.0,
      "repLayout": "2LDK",
      "yearMin": 2017,
      "yearMax": 2026,
      "station": "豊洲",
      "walkMin": 4,
      "builtYear": null,
      "ageYears": null,
      "seismic": "耐震",
      "floors": 48,
      "totalUnits": 1063,
      "address": "東京都江東区豊洲3丁目4",
      "modelName": "toyosu_6",
      "photoUrl": "https://www.wangananalytics.com/images/properties/toyosu_6.jpg",
      "facilities": {
        "プール": false,
        "ジム": false,
        "バー": false,
        "サウナ": false,
        "コンビニ": false,
        "内廊下": true,
        "オール電化": false
      },
      "specsPending": false,
      "scores": {
        "liv": 68,
        "asset": 98,
        "fac": 48,
        "loc": 92,
        "size": 70
      },
      "realFields": [
        "tsuboPrice",
        "trendPct",
        "txCount",
        "medianSqm",
        "repLayout",
        "station",
        "walkMin",
        "builtYear",
        "seismic",
        "totalUnits",
        "facilities",
        "photoUrl",
        "scores.asset",
        "scores.size",
        "scores.fac",
        "scores.loc",
        "scores.liv"
      ],
      "id": "WM042"
    },
    {
      "name": "アーバンドック パークシティ豊洲 タワーB",
      "area": "豊洲",
      "tsuboPrice": 619,
      "tsuboWindowMonths": 3,
      "txInWindow": 1,
      "tsuboAll": 455,
      "trendPct": 107.3,
      "txCount": 49,
      "medianSqm": 80.0,
      "repLayout": "3LDK",
      "yearMin": 2017,
      "yearMax": 2026,
      "station": "豊洲",
      "walkMin": 6,
      "builtYear": 2007,
      "ageYears": 19,
      "seismic": "制震",
      "floors": 32,
      "totalUnits": 420,
      "address": "東京都江東区豊洲2丁目5-2",
      "modelName": "toyosu_4",
      "photoUrl": "https://www.wangananalytics.com/images/properties/toyosu_4.jpg",
      "facilities": {
        "プール": true,
        "ジム": false,
        "バー": true,
        "サウナ": true,
        "コンビニ": true,
        "内廊下": true,
        "オール電化": false
      },
      "specsPending": false,
      "scores": {
        "liv": 72,
        "asset": 98,
        "fac": 94,
        "loc": 88,
        "size": 73
      },
      "realFields": [
        "tsuboPrice",
        "trendPct",
        "txCount",
        "medianSqm",
        "repLayout",
        "station",
        "walkMin",
        "builtYear",
        "seismic",
        "totalUnits",
        "facilities",
        "photoUrl",
        "scores.asset",
        "scores.size",
        "scores.fac",
        "scores.loc",
        "scores.liv"
      ],
      "id": "WM043"
    },
    {
      "name": "シティタワーズ豊洲 ザ・シンボル",
      "area": "豊洲",
      "tsuboPrice": 616,
      "tsuboWindowMonths": 3,
      "txInWindow": 4,
      "tsuboAll": 421,
      "trendPct": 113.5,
      "txCount": 248,
      "medianSqm": 73.0,
      "repLayout": "2LDK",
      "yearMin": 2017,
      "yearMax": 2026,
      "station": "豊洲",
      "walkMin": 9,
      "builtYear": 2009,
      "ageYears": 17,
      "seismic": "制震",
      "floors": 44,
      "totalUnits": 850,
      "address": "東京都江東区豊洲3丁目6-8",
      "modelName": "toyosu_5",
      "photoUrl": "https://www.wangananalytics.com/images/properties/toyosu_5.jpg",
      "facilities": {
        "プール": false,
        "ジム": false,
        "バー": false,
        "サウナ": false,
        "コンビニ": false,
        "内廊下": true,
        "オール電化": false
      },
      "specsPending": false,
      "scores": {
        "liv": 71,
        "asset": 98,
        "fac": 48,
        "loc": 84,
        "size": 66
      },
      "realFields": [
        "tsuboPrice",
        "trendPct",
        "txCount",
        "medianSqm",
        "repLayout",
        "station",
        "walkMin",
        "builtYear",
        "seismic",
        "totalUnits",
        "facilities",
        "photoUrl",
        "scores.asset",
        "scores.size",
        "scores.fac",
        "scores.loc",
        "scores.liv"
      ],
      "id": "WM044"
    },
    {
      "name": "パークタワー豊洲",
      "area": "豊洲",
      "tsuboPrice": 578,
      "tsuboWindowMonths": 6,
      "txInWindow": 1,
      "tsuboAll": 371,
      "trendPct": 100.9,
      "txCount": 57,
      "medianSqm": 70.0,
      "repLayout": "2LDK",
      "yearMin": 2017,
      "yearMax": 2026,
      "station": "豊洲",
      "walkMin": 5,
      "builtYear": 2013,
      "ageYears": 13,
      "seismic": "制震",
      "floors": 19,
      "totalUnits": 185,
      "address": "東京都江東区豊洲4丁目11-5",
      "modelName": "toyosu_11",
      "photoUrl": "https://www.wangananalytics.com/images/properties/toyosu_11.jpg",
      "facilities": {
        "プール": false,
        "ジム": false,
        "バー": false,
        "サウナ": false,
        "コンビニ": false,
        "内廊下": true,
        "オール電化": false
      },
      "specsPending": false,
      "scores": {
        "liv": 74,
        "asset": 98,
        "fac": 48,
        "loc": 90,
        "size": 63
      },
      "realFields": [
        "tsuboPrice",
        "trendPct",
        "txCount",
        "medianSqm",
        "repLayout",
        "station",
        "walkMin",
        "builtYear",
        "seismic",
        "totalUnits",
        "facilities",
        "photoUrl",
        "scores.asset",
        "scores.size",
        "scores.fac",
        "scores.loc",
        "scores.liv"
      ],
      "id": "WM045"
    },
    {
      "name": "プライヴブルー東京",
      "area": "豊洲",
      "tsuboPrice": 549,
      "tsuboWindowMonths": 6,
      "txInWindow": 1,
      "tsuboAll": 343,
      "trendPct": 101.7,
      "txCount": 53,
      "medianSqm": 80.0,
      "repLayout": "3LDK",
      "yearMin": 2017,
      "yearMax": 2026,
      "station": "豊洲",
      "walkMin": 5,
      "builtYear": 2005,
      "ageYears": 21,
      "seismic": "耐震",
      "floors": 20,
      "totalUnits": 513,
      "address": "東京都江東区豊洲4丁目10-18",
      "modelName": "toyosu_14",
      "photoUrl": "https://www.wangananalytics.com/images/properties/toyosu_14.jpg",
      "facilities": {
        "プール": false,
        "ジム": false,
        "バー": false,
        "サウナ": false,
        "コンビニ": false,
        "内廊下": false,
        "オール電化": false
      },
      "specsPending": false,
      "scores": {
        "liv": 58,
        "asset": 98,
        "fac": 38,
        "loc": 90,
        "size": 73
      },
      "realFields": [
        "tsuboPrice",
        "trendPct",
        "txCount",
        "medianSqm",
        "repLayout",
        "station",
        "walkMin",
        "builtYear",
        "seismic",
        "totalUnits",
        "facilities",
        "photoUrl",
        "scores.asset",
        "scores.size",
        "scores.fac",
        "scores.loc",
        "scores.liv"
      ],
      "id": "WM046"
    },
    {
      "name": "スターコート豊洲",
      "area": "豊洲",
      "tsuboPrice": 484,
      "tsuboWindowMonths": 3,
      "txInWindow": 1,
      "tsuboAll": 313,
      "trendPct": 100.0,
      "txCount": 106,
      "medianSqm": 76.0,
      "repLayout": "3LDK",
      "yearMin": 2017,
      "yearMax": 2026,
      "station": "豊洲",
      "walkMin": 4,
      "builtYear": 2007,
      "ageYears": 19,
      "seismic": "耐震",
      "floors": 18,
      "totalUnits": 740,
      "address": "東京都江東区豊洲4丁目11-20",
      "modelName": "toyosu_13",
      "photoUrl": "https://www.wangananalytics.com/images/properties/toyosu_13.jpg",
      "facilities": {
        "プール": false,
        "ジム": false,
        "バー": false,
        "サウナ": false,
        "コンビニ": false,
        "内廊下": false,
        "オール電化": false
      },
      "specsPending": false,
      "scores": {
        "liv": 59,
        "asset": 98,
        "fac": 38,
        "loc": 92,
        "size": 69
      },
      "realFields": [
        "tsuboPrice",
        "trendPct",
        "txCount",
        "medianSqm",
        "repLayout",
        "station",
        "walkMin",
        "builtYear",
        "seismic",
        "totalUnits",
        "facilities",
        "photoUrl",
        "scores.asset",
        "scores.size",
        "scores.fac",
        "scores.loc",
        "scores.liv"
      ],
      "id": "WM047"
    },
    {
      "name": "豊洲シエルタワー",
      "area": "豊洲",
      "tsuboPrice": 482,
      "tsuboWindowMonths": 24,
      "txInWindow": 1,
      "tsuboAll": 390,
      "trendPct": 40.9,
      "txCount": 17,
      "medianSqm": 61.0,
      "repLayout": "2LDK",
      "yearMin": 2017,
      "yearMax": 2024,
      "station": "豊洲",
      "walkMin": 1,
      "builtYear": 2006,
      "ageYears": 20,
      "seismic": "耐震",
      "floors": 40,
      "totalUnits": 565,
      "address": "東京都江東区豊洲5丁目5-1",
      "modelName": "toyosu_8",
      "photoUrl": "https://www.wangananalytics.com/images/properties/toyosu_8.jpg",
      "facilities": {
        "プール": false,
        "ジム": false,
        "バー": false,
        "サウナ": false,
        "コンビニ": true,
        "内廊下": false,
        "オール電化": false
      },
      "specsPending": false,
      "scores": {
        "liv": 59,
        "asset": 73,
        "fac": 48,
        "loc": 96,
        "size": 54
      },
      "realFields": [
        "tsuboPrice",
        "trendPct",
        "txCount",
        "medianSqm",
        "repLayout",
        "station",
        "walkMin",
        "builtYear",
        "seismic",
        "totalUnits",
        "facilities",
        "photoUrl",
        "scores.asset",
        "scores.size",
        "scores.fac",
        "scores.loc",
        "scores.liv"
      ],
      "id": "WM048"
    },
    {
      "name": "東京フロントコート",
      "area": "豊洲",
      "tsuboPrice": 480,
      "tsuboWindowMonths": 3,
      "txInWindow": 1,
      "tsuboAll": 308,
      "trendPct": 89.7,
      "txCount": 90,
      "medianSqm": 86.0,
      "repLayout": "3LDK",
      "yearMin": 2017,
      "yearMax": 2026,
      "station": "豊洲",
      "walkMin": 4,
      "builtYear": 2005,
      "ageYears": 21,
      "seismic": "制震",
      "floors": 20,
      "totalUnits": 981,
      "address": "東京都江東区豊洲4丁目9-13",
      "modelName": "toyosu_12",
      "photoUrl": "https://www.wangananalytics.com/images/properties/toyosu_12.jpg",
      "facilities": {
        "プール": false,
        "ジム": false,
        "バー": true,
        "サウナ": false,
        "コンビニ": false,
        "内廊下": false,
        "オール電化": false
      },
      "specsPending": false,
      "scores": {
        "liv": 62,
        "asset": 95,
        "fac": 48,
        "loc": 92,
        "size": 79
      },
      "realFields": [
        "tsuboPrice",
        "trendPct",
        "txCount",
        "medianSqm",
        "repLayout",
        "station",
        "walkMin",
        "builtYear",
        "seismic",
        "totalUnits",
        "facilities",
        "photoUrl",
        "scores.asset",
        "scores.size",
        "scores.fac",
        "scores.loc",
        "scores.liv"
      ],
      "id": "WM049"
    }
  ]
}